viindex/__init__.py
viindex/test.py
viindex/viindex.py
viindex-0.0.1.dist-info/METADATA
viindex-0.0.1.dist-info/WHEEL
viindex-0.0.1.dist-info/licenses/LICENSE
viindex-0.0.1.dist-info/RECORD
