Metadata-Version: 2.4
Name: viindex
Version: 0.0.1
Summary: Viindex is a Python package that provides a video indexing database for fast and efficient querying of video content.
Project-URL: Homepage, https://github.com/torayeff/viindex
Project-URL: Issues, https://github.com/torayeff/viindex/issues
Author-email: Your Name <youremail@example.com>
License-File: LICENSE
Classifier: License :: OSI Approved :: Apache Software License
Classifier: Operating System :: OS Independent
Classifier: Programming Language :: Python :: 3
Requires-Python: >=3.8
